<?xml version="1.0" encoding="utf-8" ?>
<XMLDocContent PageName="cobalt.graphics.ITextureBuffer.ElementCountPerPixelFromFormat" Title="ElementCountPerPixelFromFormat method" xmlns="http://www.cobaltrenderer.com/schema/XMLDocSchema.xsd">
  <Paragraph>
    <PageRef PageName="cobalt.graphics.Welcome">Home</PageRef> ->
    <PageRef PageName="cobalt.graphics.ITextureBuffer">ITextureBuffer</PageRef> ->
    ElementCountPerPixelFromFormat
  </Paragraph>
  <Section Title="Description">
    <Paragraph>
      The <TypeRef>ElementCountPerPixelFromFormat</TypeRef> method returns the number of elements in each image pixel for the specified image format.
    </Paragraph>
  </Section>
  <Section Title="Usage">
    <Code Language="C++"><![CDATA[constexpr static size_t ElementCountPerPixelFromFormat(SourceImageFormat imageFormat);
constexpr static size_t ElementCountPerPixelFromFormat(ImageFormat imageFormat);]]></Code>
    <SubSection Title="Argument list">
      <ArgumentList>
        <ArgumentListEntry Type="SourceImageFormat" Name="imageFormat">
          The image format to query.
        </ArgumentListEntry>
      </ArgumentList>
    </SubSection>
    <SubSection Title="Return value">
      <ReturnValue Type="constexpr static size_t">
        The number of scalar elements contained in each pixel or texel entry for the specified image format.
      </ReturnValue>
    </SubSection>
  </Section>
  <Section Title="See also">
    <PageRefList>
      <PageRefListEntry PageName="cobalt.graphics.ITextureBuffer">ITextureBuffer</PageRefListEntry>
    </PageRefList>
  </Section>
</XMLDocContent>
