<?xml version="1.0" encoding="utf-8" ?>
<XMLDocContent PageName="cobalt.graphics.IStateGroupNode.RemoveComputeTask" Title="RemoveComputeTask method" xmlns="http://www.cobaltrenderer.com/schema/XMLDocSchema.xsd">
  <Paragraph>
    <PageRef PageName="cobalt.graphics.Welcome">Home</PageRef> ->
    <PageRef PageName="cobalt.graphics.IStateGroupNode">IStateGroupNode</PageRef> ->
    RemoveComputeTask
  </Paragraph>
  <Section Title="Description">
    <Paragraph>
      The <TypeRef>RemoveComputeTask</TypeRef> method removes the previously set compute task for this node.
    </Paragraph>
  </Section>
  <Section Title="Usage">
    <Code Language="C++"><![CDATA[void RemoveComputeTask();]]></Code>
  </Section>
  <Section Title="See also">
    <PageRefList>
      <PageRefListEntry PageName="cobalt.graphics.IStateGroupNode">IStateGroupNode</PageRefListEntry>
    </PageRefList>
  </Section>
</XMLDocContent>
